bitcoinscript/__init__.py
bitcoinscript/address.py
bitcoinscript/basic.py
bitcoinscript/compose.py
bitcoinscript/format.py
bitcoinscript/misc.py
bitcoinscript/opcode.py
bitcoinscript/samples.py
bitcoinscript/script.py
bitcoinscript/shell.py
bitcoinscript/signature.py
bitcoinscript/verify.py
bitcoinscript/version.py
bitcoinscript/debugger/__init__.py
bitcoinscript/debugger/dbg.py
bitcoinscript/debugger/execution.py
bitcoinscript/debugger/utils.py
bitcoinscript-0.2.0.dist-info/DESCRIPTION.rst
bitcoinscript-0.2.0.dist-info/METADATA
bitcoinscript-0.2.0.dist-info/RECORD
bitcoinscript-0.2.0.dist-info/WHEEL
bitcoinscript-0.2.0.dist-info/metadata.json
bitcoinscript-0.2.0.dist-info/top_level.txt
