Metadata-Version: 2.0
Name: bitcoinscript
Version: 0.2.0
Summary: Bitcoin Script Debugger and Interactive Shell
Home-page: https://github.com/fungibit/bitcoinscript
Author: fungibit
Author-email: fungibit@yandex.com
License: MIT
Keywords: bitcoin,script,bitcoin-script,blockchain
Platform: POSIX
Platform: Windows
